whatsappCli/__init__.py
whatsappCli/__main__.py
whatsappCli/feed/__init__.py
whatsappCli/feed/feeder.py
whatsappCli/feed/pb_feeder.py
whatsappCli/feed/pb_stream.py
whatsappCli/feed/data/reply.json
whatsappCli/ui/__init__.py
whatsappCli/ui/cli.py
whatsappCli/ui/curses_ui.py
whatsappCli/ui/ui.py
whatsapp_cli-0.1.3.dist-info/LICENSE
whatsapp_cli-0.1.3.dist-info/METADATA
whatsapp_cli-0.1.3.dist-info/WHEEL
whatsapp_cli-0.1.3.dist-info/entry_points.txt
whatsapp_cli-0.1.3.dist-info/top_level.txt
whatsapp_cli-0.1.3.dist-info/RECORD
