Metadata-Version: 2.1
Name: whatsapp-cli
Version: 0.1.3
Summary: CLI for whatsapp
Home-page: https://github.com/yausername/whatsapp-cli
Author: yausername
License: MIT
Keywords: whatsapp,pushbullet,whatsapp cli,chat bots
Platform: UNKNOWN
Classifier: Environment :: Console
Classifier: Environment :: Console :: Curses
Classifier: License :: OSI Approved :: MIT License
Requires-Dist: requests
Requires-Dist: websocket-client
Requires-Dist: click
